ruth/__init__.py
ruth/constants.py
ruth/__pycache__/__init__.cpython-38.pyc
ruth/__pycache__/constants.cpython-38.pyc
ruth/cli/__init__.py
ruth/cli/cli.py
ruth/cli/constants.py
ruth/cli/utills.py
ruth/cli/data/banner.txt
ruth/nlu/__init__.py
ruth/nlu/config.py
ruth/nlu/constants.py
ruth/nlu/elements.py
ruth/nlu/model.py
ruth/nlu/registry.py
ruth/nlu/train.py
ruth/nlu/utils.py
ruth/nlu/__pycache__/__init__.cpython-38.pyc
ruth/nlu/__pycache__/constants.cpython-38.pyc
ruth/nlu/__pycache__/elements.cpython-38.pyc
ruth/nlu/__pycache__/registry.cpython-38.pyc
ruth/nlu/classifiers/__init__.py
ruth/nlu/classifiers/constants.py
ruth/nlu/classifiers/hf_classifier.py
ruth/nlu/classifiers/naive_bayes_classifier.py
ruth/nlu/classifiers/ruth_classifier.py
ruth/nlu/classifiers/svm_classifier.py
ruth/nlu/classifiers/__pycache__/__init__.cpython-38.pyc
ruth/nlu/classifiers/__pycache__/constants.cpython-38.pyc
ruth/nlu/classifiers/__pycache__/hf_classifier.cpython-38.pyc
ruth/nlu/classifiers/__pycache__/naive_bayes_classifier.cpython-38.pyc
ruth/nlu/classifiers/__pycache__/ruth_classifier.cpython-38.pyc
ruth/nlu/classifiers/__pycache__/svm_classifier.cpython-38.pyc
ruth/nlu/featurizers/__init__.py
ruth/nlu/featurizers/featurizer.py
ruth/nlu/featurizers/__pycache__/__init__.cpython-38.pyc
ruth/nlu/featurizers/__pycache__/featurizer.cpython-38.pyc
ruth/nlu/featurizers/dense_featurizers/__init__.py
ruth/nlu/featurizers/dense_featurizers/dense_featurizer.py
ruth/nlu/featurizers/dense_featurizers/fast_text.py
ruth/nlu/featurizers/dense_featurizers/__pycache__/__init__.cpython-38.pyc
ruth/nlu/featurizers/dense_featurizers/__pycache__/dense_featurizer.cpython-38.pyc
ruth/nlu/featurizers/dense_featurizers/__pycache__/fast_text.cpython-38.pyc
ruth/nlu/featurizers/sparse_featurizers/__init__.py
ruth/nlu/featurizers/sparse_featurizers/constants.py
ruth/nlu/featurizers/sparse_featurizers/count_vector_featurizer.py
ruth/nlu/featurizers/sparse_featurizers/sparse_featurizer.py
ruth_nlu-0.0.6.dist-info/METADATA
ruth_nlu-0.0.6.dist-info/WHEEL
ruth_nlu-0.0.6.dist-info/entry_points.txt
ruth_nlu-0.0.6.dist-info/top_level.txt
ruth_nlu-0.0.6.dist-info/RECORD
